easy_rule_engine/__init__.py
easy_rule_engine/core.py
easy_rule_engine/py.typed
easy_rule_engine-0.1.0.dist-info/licenses/LICENSE
easy_rule_engine-0.1.0.dist-info/METADATA
easy_rule_engine-0.1.0.dist-info/WHEEL
easy_rule_engine-0.1.0.dist-info/top_level.txt
easy_rule_engine-0.1.0.dist-info/RECORD
