Metadata-Version: 2.4
Name: easy-rule-engine
Version: 0.1.0
Summary: A tiny, composable, extensible rule engine for Python (Specification + Transformer).
Author: kingsley
License-Expression: MIT
Project-URL: Homepage, https://github.com/kingsleywang1984/easy-rule-engine
Project-URL: Source, https://github.com/kingsleywang1984/easy-rule-engine
Project-URL: Issues, https://github.com/kingsleywang1984/easy-rule-engine/issues
Keywords: rule-engine,specification,strategy,pipeline
Classifier: Development Status :: 3 - Alpha
Classifier: Intended Audience :: Developers
Classifier: Programming Language :: Python :: 3
Classifier: Programming Language :: Python :: 3 :: Only
Classifier: Programming Language :: Python :: 3.8
Classifier: Programming Language :: Python :: 3.9
Classifier: Programming Language :: Python :: 3.10
Classifier: Programming Language :: Python :: 3.11
Classifier: Programming Language :: Python :: 3.12
Classifier: Programming Language :: Python :: 3.13
Classifier: Operating System :: OS Independent
Classifier: Typing :: Typed
Requires-Python: >=3.8
License-File: LICENSE
Dynamic: license-file
